{
  "name": "RoactAlignment",
  "tree": {
    "$className": "Folder",
    "Packages": {
      "$path": "Packages"
    },
    "Modules": {
      "$className": "Folder",
      "RobloxJSPolyfill": {
        "$path": "modules/roblox-js-polyfill/src"
      },
      "React": {
        "$path": "modules/react/src"
      },
      "ReactReconciler": {
        "$path": "modules/react-reconciler/src"
      },
      "RobloxJest": {
        "$path": "modules/roblox-jest/src"
      },
      "Scheduler": {
        "$path": "modules/scheduler/src"
      },
      "Shared": {
        "$path": "modules/shared/src"
      }
    }
  }
}
